fernet_keyring_tempfile/__init__.py
fernet_keyring_tempfile-0.1.0.dist-info/METADATA
fernet_keyring_tempfile-0.1.0.dist-info/WHEEL
fernet_keyring_tempfile-0.1.0.dist-info/RECORD
