Metadata-Version: 2.3
Name: fernet_keyring_tempfile
Version: 0.1.0
Summary: Use cryptography.Fernet to encrypt and store a tempfile, automatically store the key in keyring. Indended to thrawrt only the most basic filesystem scans for plaintext tokens.
Project-URL: Homepage, https://github.com/thehappycheese/fernet_keyring_tempfile
Author-email: thehappycheese <2748120+thehappycheese@users.noreply.github.com>
License: Copyright (c) 2004 thehappycheese
Requires-Python: >=3.8
Requires-Dist: cryptography
Requires-Dist: keyring
